{
  "": {
    "conditions": [
      {
        "id": "on-state-enter",
        "scriptName": "OnStateEnter",
        "isTrigger": true,
        "params": [
          {
            "id": "state",
            "type": "string"
          }
        ]
      },
      {
        "id": "on-state-exit",
        "scriptName": "OnStateExit",
        "isTrigger": true,
        "params": [
          {
            "id": "state",
            "type": "string"
          }
        ]
      },
      {
        "id": "every-tick-for-state",
        "highlight": true,
        "scriptName": "EveryTickForState",
        "params": [
          {
            "id": "state",
            "type": "string"
          }
        ]
      },
      {
        "id": "compare-current-state",
        "scriptName": "CompareCurrentState",
        "params": [
          {
            "id": "comparison",
            "type": "cmp"
          },
          {
            "id": "state",
            "type": "string"
          }
        ]
      },
      {
        "id": "compare-previous-state",
        "scriptName": "ComparePreviousState",
        "params": [
          {
            "id": "comparison",
            "type": "cmp"
          },
          {
            "id": "state",
            "type": "string"
          }
        ]
      }
    ],
    "actions": [
      {
        "id": "set-state",
        "scriptName": "SetState",
        "highlight": true,
        "params": [
          {
            "id": "state",
            "type": "string"
          }
        ]
      }
    ],
    "expressions": [
      {
        "id": "current-state",
        "expressionName": "CurrentState",
        "returnType": "string"
      },
      {
        "id": "previous-state",
        "expressionName": "PreviousState",
        "returnType": "string"
      }
    ]
  }
}